diophila/__init__.py
diophila/api_caller.py
diophila/endpoints.py
diophila/openalex.py
diophila-0.4.0.dist-info/LICENSE
diophila-0.4.0.dist-info/METADATA
diophila-0.4.0.dist-info/WHEEL
diophila-0.4.0.dist-info/top_level.txt
diophila-0.4.0.dist-info/RECORD
