Metadata-Version: 2.1
Name: diophila
Version: 0.4.0
Summary: Python API Wrapper for OpenAlex
Home-page: https://github.com/smierz/diophila
Author: Sandra Mierz
License: BSD-3
Project-URL: Bug Tracker, https://github.com/smierz/diophila/issues
Keywords: openalex
Platform: UNKNOWN
Classifier: Programming Language :: Python :: 3
Classifier: License :: OSI Approved :: BSD License
Classifier: Operating System :: OS Independent
Classifier: Intended Audience :: Science/Research
License-File: LICENSE
Requires-Dist: requests (>=2.7.0)
